LICENSE
MANIFEST.in
README.rst
setup.py
pytest_html_reporter/__init__.py
pytest_html_reporter/plugin.py
pytest_html_reporter/template.py
pytest_html_reporter/time_converter.py
pytest_html_reporter.egg-info/PKG-INFO
pytest_html_reporter.egg-info/SOURCES.txt
pytest_html_reporter.egg-info/dependency_links.txt
pytest_html_reporter.egg-info/entry_points.txt
pytest_html_reporter.egg-info/requires.txt
pytest_html_reporter.egg-info/top_level.txt