Metadata-Version: 2.1
Name: pytest-html-reporter
Version: 0.2.9
Summary: Generates a static html report based on pytest framework
Home-page: https://github.com/prashanth-sams/pytest-html-reporter
Author: Prashanth Sams
Author-email: sams.prashanth@gmail.com
Maintainer: Prashanth Sams
Maintainer-email: sams.prashanth@gmail.com
License: MIT
Keywords: pytest,py.test,html,reporter,report
Platform: UNKNOWN
Classifier: Framework :: Pytest
Classifier: Topic :: Software Development :: Testing
Classifier: Programming Language :: Python
Classifier: Operating System :: OS Independent
Classifier: License :: OSI Approved :: MIT License
Requires-Python: >=3.5
License-File: LICENSE
